LICENSE
README.md
ebt.conf
plans.py
setup.cfg
setup.py
ebt.egg-info/PKG-INFO
ebt.egg-info/SOURCES.txt
ebt.egg-info/dependency_links.txt
ebt.egg-info/entry_points.txt
ebt.egg-info/requires.txt
ebt.egg-info/top_level.txt
ebt_cleaner/__init__.py
ebt_cleaner/cleaner.py
ebt_cli/__init__.py
ebt_cli/__version__.py
ebt_cli/cli.py
ebt_cli/ddd.py
ebt_cli/ebt.spec
ebt_cli/log.py
ebt_cloud/__init__.py
ebt_cloud/amazon.py
ebt_db/__init__.py
ebt_db/mysql.py
ebt_files/__init__.py
ebt_files/archive.py
ebt_files/dd.py
ebt_files/ddd.py
ebt_files/rsync.py
ebt_jobs/__init__.py
ebt_jobs/amazon.py
ebt_jobs/btrfs.py
ebt_jobs/mysql.py
ebt_jobs/rsync.py
ebt_jobs/s3.py
ebt_jobs/vm.py
ebt_system/__init__.py
ebt_system/btrfs.py
ebt_system/lvm.py
ebt_system/system.py
ebt_virt/__init__.py
ebt_virt/libvirt_helper.py