Metadata-Version: 2.1
Name: ebt
Version: 2.0.96
Summary: Flexible backup framework
Home-page: https://github.com/larrabee/ebt
Author: larrabee
Author-email: kafatron@gmail.com
License: GPLv3
Keywords: diff-dd diff disk dump tool
Platform: UNKNOWN
Classifier: Development Status :: 5 - Production/Stable
Classifier: Environment :: Console
Classifier: Intended Audience :: System Administrators
Classifier: Operating System :: POSIX :: Linux
Classifier: Operating System :: Unix
Classifier: Topic :: Utilities
Classifier: Topic :: System :: Archiving :: Backup
Classifier: License :: OSI Approved :: GNU General Public License v3 (GPLv3)
Classifier: Programming Language :: Python :: 2.7
Classifier: Programming Language :: Python :: 3
License-File: LICENSE
